{
    "image_path": "DRG_model\\\\output\\\\step0-digit-600kb\\\\09_page_2.png",
    "recognition_time_sec": 1.4765582084655762,
    "pages": [
        {
            "page_index": 1,
            "results": [
                {
                    "text": "不及",
                    "score": 0.49259400367736816,
                    "bbox": [
                        [
                            22,
                            0
                        ],
                        [
                            83,
                            0
                        ],
                        [
                            83,
                            15
                        ],
                        [
                            22,
                            15
                        ]
                    ]
                },
                {
                    "text": "手术及",
                    "score": 0.9961239695549011,
                    "bbox": [
                        [
                            187,
                            0
                        ],
                        [
                            291,
                            0
                        ],
                        [
                            291,
                            36
                        ],
                        [
                            187,
                            36
                        ]
                    ]
                },
                {
                    "text": "手术级",
                    "score": 0.9965839982032776,
                    "bbox": [
                        [
                            324,
                            0
                        ],
                        [
                            440,
                            0
                        ],
                        [
                            440,
                            51
                        ],
                        [
                            324,
                            51
                        ]
                    ]
                },
                {
                    "text": "于不汉探作达师",
                    "score": 0.44533467292785645,
                    "bbox": [
                        [
                            693,
                            0
                        ],
                        [
                            920,
                            0
                        ],
                        [
                            920,
                            18
                        ],
                        [
                            693,
                            18
                        ]
                    ]
                },
                {
                    "text": "切口愈合",
                    "score": 0.9993644952774048,
                    "bbox": [
                        [
                            1034,
                            0
                        ],
                        [
                            1169,
                            0
                        ],
                        [
                            1169,
                            36
                        ],
                        [
                            1034,
                            36
                        ]
                    ]
                },
                {
                    "text": "麻醉医",
                    "score": 0.9994609951972961,
                    "bbox": [
                        [
                            1328,
                            0
                        ],
                        [
                            1437,
                            0
                        ],
                        [
                            1437,
                            32
                        ],
                        [
                            1328,
                            32
                        ]
                    ]
                },
                {
                    "text": "操作编码",
                    "score": 0.8722672462463379,
                    "bbox": [
                        [
                            0,
                            10
                        ],
                        [
                            120,
                            10
                        ],
                        [
                            120,
                            68
                        ],
                        [
                            0,
                            68
                        ]
                    ]
                },
                {
                    "text": "操作日期",
                    "score": 0.999606728553772,
                    "bbox": [
                        [
                            184,
                            26
                        ],
                        [
                            326,
                            26
                        ],
                        [
                            326,
                            84
                        ],
                        [
                            184,
                            84
                        ]
                    ]
                },
                {
                    "text": "手术及操作名称",
                    "score": 0.9988726377487183,
                    "bbox": [
                        [
                            432,
                            19
                        ],
                        [
                            670,
                            19
                        ],
                        [
                            670,
                            69
                        ],
                        [
                            432,
                            69
                        ]
                    ]
                },
                {
                    "text": "麻醉方式",
                    "score": 0.9987215399742126,
                    "bbox": [
                        [
                            1180,
                            14
                        ],
                        [
                            1328,
                            14
                        ],
                        [
                            1328,
                            72
                        ],
                        [
                            1180,
                            72
                        ]
                    ]
                },
                {
                    "text": "术者",
                    "score": 0.9983561038970947,
                    "bbox": [
                        [
                            703,
                            30
                        ],
                        [
                            788,
                            30
                        ],
                        [
                            788,
                            85
                        ],
                        [
                            703,
                            85
                        ]
                    ]
                },
                {
                    "text": "I助",
                    "score": 0.9955475926399231,
                    "bbox": [
                        [
                            833,
                            32
                        ],
                        [
                            903,
                            32
                        ],
                        [
                            903,
                            85
                        ],
                        [
                            833,
                            85
                        ]
                    ]
                },
                {
                    "text": "Ⅱ助",
                    "score": 0.9259122014045715,
                    "bbox": [
                        [
                            946,
                            34
                        ],
                        [
                            1050,
                            34
                        ],
                        [
                            1050,
                            84
                        ],
                        [
                            946,
                            84
                        ]
                    ]
                },
                {
                    "text": "等级",
                    "score": 0.9995182752609253,
                    "bbox": [
                        [
                            1030,
                            34
                        ],
                        [
                            1108,
                            34
                        ],
                        [
                            1108,
                            82
                        ],
                        [
                            1030,
                            82
                        ]
                    ]
                },
                {
                    "text": "师",
                    "score": 0.993989109992981,
                    "bbox": [
                        [
                            1326,
                            29
                        ],
                        [
                            1371,
                            29
                        ],
                        [
                            1371,
                            78
                        ],
                        [
                            1326,
                            78
                        ]
                    ]
                },
                {
                    "text": "别",
                    "score": 0.9967533946037292,
                    "bbox": [
                        [
                            324,
                            42
                        ],
                        [
                            370,
                            42
                        ],
                        [
                            370,
                            91
                        ],
                        [
                            324,
                            91
                        ]
                    ]
                },
                {
                    "text": "2025年09",
                    "score": 0.9998802542686462,
                    "bbox": [
                        [
                            187,
                            94
                        ],
                        [
                            327,
                            94
                        ],
                        [
                            327,
                            144
                        ],
                        [
                            187,
                            144
                        ]
                    ]
                },
                {
                    "text": "2.2002",
                    "score": 0.9993450045585632,
                    "bbox": [
                        [
                            0,
                            108
                        ],
                        [
                            96,
                            108
                        ],
                        [
                            96,
                            153
                        ],
                        [
                            0,
                            153
                        ]
                    ]
                },
                {
                    "text": "胸腔镜下肺大疱",
                    "score": 0.990860641002655,
                    "bbox": [
                        [
                            434,
                            99
                        ],
                        [
                            670,
                            99
                        ],
                        [
                            670,
                            142
                        ],
                        [
                            434,
                            142
                        ]
                    ]
                },
                {
                    "text": "三级",
                    "score": 0.9998006820678711,
                    "bbox": [
                        [
                            345,
                            120
                        ],
                        [
                            422,
                            120
                        ],
                        [
                            422,
                            167
                        ],
                        [
                            345,
                            167
                        ]
                    ]
                },
                {
                    "text": "刘X涛",
                    "score": 0.9562953114509583,
                    "bbox": [
                        [
                            681,
                            117
                        ],
                        [
                            785,
                            117
                        ],
                        [
                            785,
                            165
                        ],
                        [
                            681,
                            165
                        ]
                    ]
                },
                {
                    "text": "张X阳",
                    "score": 0.9919307827949524,
                    "bbox": [
                        [
                            804,
                            119
                        ],
                        [
                            902,
                            119
                        ],
                        [
                            902,
                            164
                        ],
                        [
                            804,
                            164
                        ]
                    ]
                },
                {
                    "text": "李X悦",
                    "score": 0.9460307955741882,
                    "bbox": [
                        [
                            927,
                            120
                        ],
                        [
                            1023,
                            120
                        ],
                        [
                            1023,
                            165
                        ],
                        [
                            927,
                            165
                        ]
                    ]
                },
                {
                    "text": "I/甲",
                    "score": 0.7954465746879578,
                    "bbox": [
                        [
                            1032,
                            123
                        ],
                        [
                            1094,
                            123
                        ],
                        [
                            1094,
                            165
                        ],
                        [
                            1032,
                            165
                        ]
                    ]
                },
                {
                    "text": "全身麻醉",
                    "score": 0.9982805252075195,
                    "bbox": [
                        [
                            1184,
                            116
                        ],
                        [
                            1329,
                            116
                        ],
                        [
                            1329,
                            167
                        ],
                        [
                            1184,
                            167
                        ]
                    ]
                },
                {
                    "text": "周X凯",
                    "score": 0.9845444560050964,
                    "bbox": [
                        [
                            1328,
                            118
                        ],
                        [
                            1427,
                            118
                        ],
                        [
                            1427,
                            163
                        ],
                        [
                            1328,
                            163
                        ]
                    ]
                },
                {
                    "text": "月05日",
                    "score": 0.9996399283409119,
                    "bbox": [
                        [
                            189,
                            137
                        ],
                        [
                            294,
                            137
                        ],
                        [
                            294,
                            185
                        ],
                        [
                            189,
                            185
                        ]
                    ]
                },
                {
                    "text": "切除术",
                    "score": 0.998968780040741,
                    "bbox": [
                        [
                            433,
                            137
                        ],
                        [
                            543,
                            137
                        ],
                        [
                            543,
                            185
                        ],
                        [
                            433,
                            185
                        ]
                    ]
                },
                {
                    "text": "2025年09",
                    "score": 0.999893307685852,
                    "bbox": [
                        [
                            190,
                            192
                        ],
                        [
                            329,
                            192
                        ],
                        [
                            329,
                            235
                        ],
                        [
                            190,
                            235
                        ]
                    ]
                },
                {
                    "text": "4.0401",
                    "score": 0.9998941421508789,
                    "bbox": [
                        [
                            0,
                            206
                        ],
                        [
                            96,
                            206
                        ],
                        [
                            96,
                            248
                        ],
                        [
                            0,
                            248
                        ]
                    ]
                },
                {
                    "text": "二级",
                    "score": 0.9998936057090759,
                    "bbox": [
                        [
                            345,
                            212
                        ],
                        [
                            425,
                            212
                        ],
                        [
                            425,
                            259
                        ],
                        [
                            345,
                            259
                        ]
                    ]
                },
                {
                    "text": "胸腔闭式引流术",
                    "score": 0.9987873435020447,
                    "bbox": [
                        [
                            435,
                            211
                        ],
                        [
                            674,
                            211
                        ],
                        [
                            674,
                            255
                        ],
                        [
                            435,
                            255
                        ]
                    ]
                },
                {
                    "text": "刘X涛",
                    "score": 0.9544036984443665,
                    "bbox": [
                        [
                            679,
                            209
                        ],
                        [
                            786,
                            209
                        ],
                        [
                            786,
                            257
                        ],
                        [
                            679,
                            257
                        ]
                    ]
                },
                {
                    "text": "张X阳",
                    "score": 0.9922052025794983,
                    "bbox": [
                        [
                            803,
                            211
                        ],
                        [
                            903,
                            211
                        ],
                        [
                            903,
                            259
                        ],
                        [
                            803,
                            259
                        ]
                    ]
                },
                {
                    "text": "李X悦",
                    "score": 0.9687450528144836,
                    "bbox": [
                        [
                            926,
                            213
                        ],
                        [
                            1024,
                            213
                        ],
                        [
                            1024,
                            258
                        ],
                        [
                            926,
                            258
                        ]
                    ]
                },
                {
                    "text": "/甲",
                    "score": 0.9572135210037231,
                    "bbox": [
                        [
                            1031,
                            217
                        ],
                        [
                            1092,
                            217
                        ],
                        [
                            1092,
                            257
                        ],
                        [
                            1031,
                            257
                        ]
                    ]
                },
                {
                    "text": "局部麻醉",
                    "score": 0.9985408782958984,
                    "bbox": [
                        [
                            1186,
                            215
                        ],
                        [
                            1328,
                            215
                        ],
                        [
                            1328,
                            258
                        ],
                        [
                            1186,
                            258
                        ]
                    ]
                },
                {
                    "text": "周X凯",
                    "score": 0.9861192107200623,
                    "bbox": [
                        [
                            1327,
                            216
                        ],
                        [
                            1425,
                            216
                        ],
                        [
                            1425,
                            257
                        ],
                        [
                            1327,
                            257
                        ]
                    ]
                },
                {
                    "text": "月01日",
                    "score": 0.9985918998718262,
                    "bbox": [
                        [
                            190,
                            229
                        ],
                        [
                            295,
                            229
                        ],
                        [
                            295,
                            278
                        ],
                        [
                            190,
                            278
                        ]
                    ]
                },
                {
                    "text": "离院方式",
                    "score": 0.9945620894432068,
                    "bbox": [
                        [
                            0,
                            625
                        ],
                        [
                            126,
                            625
                        ],
                        [
                            126,
                            667
                        ],
                        [
                            0,
                            667
                        ]
                    ]
                },
                {
                    "text": "1",
                    "score": 0.2594817578792572,
                    "bbox": [
                        [
                            168,
                            625
                        ],
                        [
                            211,
                            625
                        ],
                        [
                            211,
                            664
                        ],
                        [
                            168,
                            664
                        ]
                    ]
                },
                {
                    "text": "1.医瞩离院2.医嘱转院，拟接收医疗机构名称：",
                    "score": 0.9951789975166321,
                    "bbox": [
                        [
                            254,
                            628
                        ],
                        [
                            961,
                            628
                        ],
                        [
                            961,
                            668
                        ],
                        [
                            254,
                            668
                        ]
                    ]
                },
                {
                    "text": ".医嘱转社区卫生服务机构/乡镇卫生院，拟接收医疗机构名称：",
                    "score": 0.9877296686172485,
                    "bbox": [
                        [
                            0,
                            663
                        ],
                        [
                            907,
                            663
                        ],
                        [
                            907,
                            708
                        ],
                        [
                            0,
                            708
                        ]
                    ]
                },
                {
                    "text": "4.非医瞩离院5.",
                    "score": 0.998358428478241,
                    "bbox": [
                        [
                            1166,
                            668
                        ],
                        [
                            1441,
                            668
                        ],
                        [
                            1441,
                            713
                        ],
                        [
                            1166,
                            713
                        ]
                    ]
                },
                {
                    "text": "亡9.其他",
                    "score": 0.9975403547286987,
                    "bbox": [
                        [
                            0,
                            701
                        ],
                        [
                            188,
                            701
                        ],
                        [
                            188,
                            746
                        ],
                        [
                            0,
                            746
                        ]
                    ]
                },
                {
                    "text": "是否有出院31天内再住院计划",
                    "score": 0.9927753210067749,
                    "bbox": [
                        [
                            0,
                            770
                        ],
                        [
                            413,
                            770
                        ],
                        [
                            413,
                            810
                        ],
                        [
                            0,
                            810
                        ]
                    ]
                },
                {
                    "text": "目",
                    "score": 0.33361509442329407,
                    "bbox": [
                        [
                            473,
                            765
                        ],
                        [
                            523,
                            765
                        ],
                        [
                            523,
                            810
                        ],
                        [
                            473,
                            810
                        ]
                    ]
                },
                {
                    "text": "1.无2.有，目的：",
                    "score": 0.9761292338371277,
                    "bbox": [
                        [
                            573,
                            768
                        ],
                        [
                            860,
                            768
                        ],
                        [
                            860,
                            814
                        ],
                        [
                            573,
                            814
                        ]
                    ]
                },
                {
                    "text": "页脑损伤患者昏迷时间：入院前",
                    "score": 0.9924390912055969,
                    "bbox": [
                        [
                            0,
                            828
                        ],
                        [
                            447,
                            828
                        ],
                        [
                            447,
                            867
                        ],
                        [
                            0,
                            867
                        ]
                    ]
                },
                {
                    "text": "0",
                    "score": 0.9448789358139038,
                    "bbox": [
                        [
                            485,
                            833
                        ],
                        [
                            511,
                            833
                        ],
                        [
                            511,
                            865
                        ],
                        [
                            485,
                            865
                        ]
                    ]
                },
                {
                    "text": "天",
                    "score": 0.9993550181388855,
                    "bbox": [
                        [
                            543,
                            831
                        ],
                        [
                            592,
                            831
                        ],
                        [
                            592,
                            869
                        ],
                        [
                            543,
                            869
                        ]
                    ]
                },
                {
                    "text": "0",
                    "score": 0.9879429936408997,
                    "bbox": [
                        [
                            626,
                            834
                        ],
                        [
                            653,
                            834
                        ],
                        [
                            653,
                            866
                        ],
                        [
                            626,
                            866
                        ]
                    ]
                },
                {
                    "text": "小时0",
                    "score": 0.9889490008354187,
                    "bbox": [
                        [
                            689,
                            831
                        ],
                        [
                            824,
                            831
                        ],
                        [
                            824,
                            874
                        ],
                        [
                            689,
                            874
                        ]
                    ]
                },
                {
                    "text": "分钟",
                    "score": 0.9994456768035889,
                    "bbox": [
                        [
                            850,
                            832
                        ],
                        [
                            929,
                            832
                        ],
                        [
                            929,
                            874
                        ],
                        [
                            850,
                            874
                        ]
                    ]
                },
                {
                    "text": "入院后0",
                    "score": 0.9842501878738403,
                    "bbox": [
                        [
                            999,
                            827
                        ],
                        [
                            1190,
                            827
                        ],
                        [
                            1190,
                            872
                        ],
                        [
                            999,
                            872
                        ]
                    ]
                },
                {
                    "text": "_天0",
                    "score": 0.8636797070503235,
                    "bbox": [
                        [
                            1204,
                            828
                        ],
                        [
                            1312,
                            828
                        ],
                        [
                            1312,
                            871
                        ],
                        [
                            1204,
                            871
                        ]
                    ]
                },
                {
                    "text": "小时",
                    "score": 0.9998984932899475,
                    "bbox": [
                        [
                            1318,
                            827
                        ],
                        [
                            1424,
                            827
                        ],
                        [
                            1424,
                            869
                        ],
                        [
                            1318,
                            869
                        ]
                    ]
                },
                {
                    "text": "分钟",
                    "score": 0.9997367858886719,
                    "bbox": [
                        [
                            43,
                            867
                        ],
                        [
                            129,
                            867
                        ],
                        [
                            129,
                            909
                        ],
                        [
                            43,
                            909
                        ]
                    ]
                },
                {
                    "text": "主院费用(元)：总费用26796.41（自付金额：）",
                    "score": 0.9094944596290588,
                    "bbox": [
                        [
                            0,
                            931
                        ],
                        [
                            718,
                            931
                        ],
                        [
                            718,
                            982
                        ],
                        [
                            0,
                            982
                        ]
                    ]
                },
                {
                    "text": ".综合医疗服务类：（1)一般医疗服务费：",
                    "score": 0.9799725413322449,
                    "bbox": [
                        [
                            0,
                            987
                        ],
                        [
                            568,
                            987
                        ],
                        [
                            568,
                            1028
                        ],
                        [
                            0,
                            1028
                        ]
                    ]
                },
                {
                    "text": "(2)一般治疗操作费：",
                    "score": 0.990061342716217,
                    "bbox": [
                        [
                            737,
                            993
                        ],
                        [
                            1019,
                            993
                        ],
                        [
                            1019,
                            1027
                        ],
                        [
                            737,
                            1027
                        ]
                    ]
                },
                {
                    "text": "(3)护理费：",
                    "score": 0.9876022934913635,
                    "bbox": [
                        [
                            1164,
                            991
                        ],
                        [
                            1331,
                            991
                        ],
                        [
                            1331,
                            1030
                        ],
                        [
                            1164,
                            1030
                        ]
                    ]
                },
                {
                    "text": "4)其他费用：",
                    "score": 0.9960352778434753,
                    "bbox": [
                        [
                            0,
                            1041
                        ],
                        [
                            202,
                            1041
                        ],
                        [
                            202,
                            1086
                        ],
                        [
                            0,
                            1086
                        ]
                    ]
                },
                {
                    "text": ".诊断类：（5)病理诊断费：",
                    "score": 0.9720855951309204,
                    "bbox": [
                        [
                            0,
                            1092
                        ],
                        [
                            377,
                            1092
                        ],
                        [
                            377,
                            1137
                        ],
                        [
                            0,
                            1137
                        ]
                    ]
                },
                {
                    "text": "(6)实验室诊断费：",
                    "score": 0.9862468838691711,
                    "bbox": [
                        [
                            656,
                            1093
                        ],
                        [
                            913,
                            1093
                        ],
                        [
                            913,
                            1132
                        ],
                        [
                            656,
                            1132
                        ]
                    ]
                },
                {
                    "text": "(7)影像学诊断费：",
                    "score": 0.9864283800125122,
                    "bbox": [
                        [
                            1176,
                            1097
                        ],
                        [
                            1435,
                            1097
                        ],
                        [
                            1435,
                            1134
                        ],
                        [
                            1176,
                            1134
                        ]
                    ]
                },
                {
                    "text": "(8)临床诊断项目费：",
                    "score": 0.9744357466697693,
                    "bbox": [
                        [
                            0,
                            1146
                        ],
                        [
                            296,
                            1146
                        ],
                        [
                            296,
                            1189
                        ],
                        [
                            0,
                            1189
                        ]
                    ]
                },
                {
                    "text": ".治疗类：（9)非手术治疗项目费：",
                    "score": 0.9816989898681641,
                    "bbox": [
                        [
                            0,
                            1195
                        ],
                        [
                            481,
                            1195
                        ],
                        [
                            481,
                            1238
                        ],
                        [
                            0,
                            1238
                        ]
                    ]
                },
                {
                    "text": "（临床物理治疗费：",
                    "score": 0.9668196439743042,
                    "bbox": [
                        [
                            777,
                            1199
                        ],
                        [
                            1027,
                            1199
                        ],
                        [
                            1027,
                            1233
                        ],
                        [
                            777,
                            1233
                        ]
                    ]
                },
                {
                    "text": "10)手术治疗费：",
                    "score": 0.9974978566169739,
                    "bbox": [
                        [
                            1,
                            1250
                        ],
                        [
                            260,
                            1250
                        ],
                        [
                            260,
                            1284
                        ],
                        [
                            1,
                            1284
                        ]
                    ]
                },
                {
                    "text": "（麻醉费：",
                    "score": 0.9515393972396851,
                    "bbox": [
                        [
                            499,
                            1247
                        ],
                        [
                            634,
                            1247
                        ],
                        [
                            634,
                            1285
                        ],
                        [
                            499,
                            1285
                        ]
                    ]
                },
                {
                    "text": "手术费：",
                    "score": 0.9969292879104614,
                    "bbox": [
                        [
                            752,
                            1250
                        ],
                        [
                            911,
                            1250
                        ],
                        [
                            911,
                            1285
                        ],
                        [
                            752,
                            1285
                        ]
                    ]
                },
                {
                    "text": ".康复类：（11)康复费：",
                    "score": 0.9618014693260193,
                    "bbox": [
                        [
                            0,
                            1297
                        ],
                        [
                            346,
                            1297
                        ],
                        [
                            346,
                            1339
                        ],
                        [
                            0,
                            1339
                        ]
                    ]
                },
                {
                    "text": "、中医类：（12)中医治疗费：",
                    "score": 0.9473016858100891,
                    "bbox": [
                        [
                            2,
                            1348
                        ],
                        [
                            394,
                            1348
                        ],
                        [
                            394,
                            1386
                        ],
                        [
                            2,
                            1386
                        ]
                    ]
                },
                {
                    "text": "．西药类：(13)西药费：",
                    "score": 0.959904670715332,
                    "bbox": [
                        [
                            6,
                            1402
                        ],
                        [
                            337,
                            1402
                        ],
                        [
                            337,
                            1440
                        ],
                        [
                            6,
                            1440
                        ]
                    ]
                },
                {
                    "text": "（抗菌药物费用：",
                    "score": 0.957630455493927,
                    "bbox": [
                        [
                            662,
                            1401
                        ],
                        [
                            881,
                            1401
                        ],
                        [
                            881,
                            1439
                        ],
                        [
                            662,
                            1439
                        ]
                    ]
                },
                {
                    "text": "中药类：（14)中成药费：",
                    "score": 0.9626684188842773,
                    "bbox": [
                        [
                            4,
                            1447
                        ],
                        [
                            362,
                            1447
                        ],
                        [
                            362,
                            1483
                        ],
                        [
                            4,
                            1483
                        ]
                    ]
                },
                {
                    "text": "(15)中草药费：",
                    "score": 0.9967024326324463,
                    "bbox": [
                        [
                            582,
                            1446
                        ],
                        [
                            801,
                            1446
                        ],
                        [
                            801,
                            1483
                        ],
                        [
                            582,
                            1483
                        ]
                    ]
                },
                {
                    "text": "、血液和血液制品类：（16)血费：",
                    "score": 0.947298526763916,
                    "bbox": [
                        [
                            2,
                            1499
                        ],
                        [
                            461,
                            1499
                        ],
                        [
                            461,
                            1538
                        ],
                        [
                            2,
                            1538
                        ]
                    ]
                },
                {
                    "text": "(17)白蛋白类制品费：",
                    "score": 0.9438371658325195,
                    "bbox": [
                        [
                            587,
                            1503
                        ],
                        [
                            911,
                            1503
                        ],
                        [
                            911,
                            1539
                        ],
                        [
                            587,
                            1539
                        ]
                    ]
                },
                {
                    "text": "(18)球蛋白类制",
                    "score": 0.9913033246994019,
                    "bbox": [
                        [
                            1213,
                            1499
                        ],
                        [
                            1448,
                            1499
                        ],
                        [
                            1448,
                            1540
                        ],
                        [
                            1213,
                            1540
                        ]
                    ]
                },
                {
                    "text": "品费：",
                    "score": 0.987515926361084,
                    "bbox": [
                        [
                            0,
                            1543
                        ],
                        [
                            86,
                            1543
                        ],
                        [
                            86,
                            1584
                        ],
                        [
                            0,
                            1584
                        ]
                    ]
                },
                {
                    "text": "19)凝血因子类制品费：",
                    "score": 0.9945468902587891,
                    "bbox": [
                        [
                            2,
                            1595
                        ],
                        [
                            330,
                            1595
                        ],
                        [
                            330,
                            1627
                        ],
                        [
                            2,
                            1627
                        ]
                    ]
                },
                {
                    "text": "(20)细胞因子类制品费：",
                    "score": 0.9945083856582642,
                    "bbox": [
                        [
                            633,
                            1595
                        ],
                        [
                            966,
                            1595
                        ],
                        [
                            966,
                            1632
                        ],
                        [
                            633,
                            1632
                        ]
                    ]
                },
                {
                    "text": ".耗材类：(21)检查用一次性医用材料费：",
                    "score": 0.9817173480987549,
                    "bbox": [
                        [
                            6,
                            1645
                        ],
                        [
                            578,
                            1645
                        ],
                        [
                            578,
                            1682
                        ],
                        [
                            6,
                            1682
                        ]
                    ]
                },
                {
                    "text": "(22)治疗用一次性医用材料费：",
                    "score": 0.993915319442749,
                    "bbox": [
                        [
                            916,
                            1644
                        ],
                        [
                            1343,
                            1644
                        ],
                        [
                            1343,
                            1686
                        ],
                        [
                            916,
                            1686
                        ]
                    ]
                },
                {
                    "text": "23)手术用一次性医用材料费：",
                    "score": 0.9973540902137756,
                    "bbox": [
                        [
                            1,
                            1695
                        ],
                        [
                            439,
                            1695
                        ],
                        [
                            439,
                            1727
                        ],
                        [
                            1,
                            1727
                        ]
                    ]
                },
                {
                    "text": "0.其他类：(24)其他费：",
                    "score": 0.970883846282959,
                    "bbox": [
                        [
                            1,
                            1744
                        ],
                        [
                            357,
                            1744
                        ],
                        [
                            357,
                            1779
                        ],
                        [
                            1,
                            1779
                        ]
                    ]
                }
            ]
        }
    ]
}